pystone/__init__.py
pystone/__version__.py
pystone/constants.py
pystone/deepl.py
pystone/languages.py
pystone/reverso.py
pystone-0.1.0.dist-info/LICENSE
pystone-0.1.0.dist-info/METADATA
pystone-0.1.0.dist-info/WHEEL
pystone-0.1.0.dist-info/entry_points.txt
pystone-0.1.0.dist-info/top_level.txt
pystone-0.1.0.dist-info/RECORD
