Metadata-Version: 2.1
Name: pystone
Version: 0.1.0
Summary: A command line tool written in Python for translating text through Reverso.
Home-page: https://github.com/GBS3/pystone
Author: Giovanni Salinas
Author-email: gbs3@protonmail.com
License: MIT License
Project-URL: Source, https://github.com/GBS3/pystone
Keywords: pystone,translation,language,python,reverso,deepl
Platform: UNKNOWN
Classifier: Development Status :: 5 - Production/Stable
Classifier: Programming Language :: Python :: 3.6
Classifier: Programming Language :: Python :: 3.7
Classifier: Programming Language :: Python :: 3.8
Classifier: Programming Language :: Python :: 3.9
Classifier: License :: OSI Approved :: MIT License
Classifier: Operating System :: OS Independent
Requires-Dist: requests
Requires-Dist: playsound
